pysenechome/__init__.py
pysenechome/converter.py
pysenechome-0.0.1.dist-info/LICENSE
pysenechome-0.0.1.dist-info/METADATA
pysenechome-0.0.1.dist-info/WHEEL
pysenechome-0.0.1.dist-info/top_level.txt
pysenechome-0.0.1.dist-info/zip-safe
pysenechome-0.0.1.dist-info/RECORD
