Metadata-Version: 2.1
Name: pysenechome
Version: 0.0.1
Summary: Library to interface a SENEC.Home battery API
Home-page: https://github.com/mailq/pysenechome
Author: Marcel Lohmann
Author-email: programming@malowa.de
License: MIT
Download-URL: https://github.com/mailq/pysenechome/tarball/0.0.1
Platform: UNKNOWN
Requires-Dist: aiohttp (<4,>3)
Requires-Dist: async-timeout (<4,>3)
Requires-Dist: attrs (>18)
